.DS_Store
RC_Functools/__init__.py
RC_Functools/rc_func.py
RC_Functools-0.0.6.dist-info/LICENSE
RC_Functools-0.0.6.dist-info/METADATA
RC_Functools-0.0.6.dist-info/WHEEL
RC_Functools-0.0.6.dist-info/top_level.txt
RC_Functools-0.0.6.dist-info/RECORD
