Metadata-Version: 2.1
Name: RC-Functools
Version: 0.0.6
Summary: Extended functional tools and None-handling for Python
Home-page: https://github.com/sorrowfulT-Rex/Python-Functools
Author: Sorrowful T-Rex
Author-email: yc4120@ic.ac.uk
License: UNKNOWN
Platform: UNKNOWN
Classifier: Programming Language :: Python :: 3
Classifier: License :: OSI Approved :: MIT License
Classifier: Operating System :: OS Independent
Requires-Python: >=3.6
